{"is_source_file": false, "format": "", "description": "", "external_files": [], "external_methods": [], "published": [], "classes": [], "methods": [], "calls": [], "search-terms": [], "state": 2, "file_id": 12, "knowledge_revision": 24, "git_revision": "4da9b3090a8d5117414e47c686a3344d637b9bc0", "hash": "f7da88c3e6010faad4860fb12cb3c90d", "format-version": 4, "code-base-name": "lead_management_frontend", "filename": "README.md", "revision_history": [{"24": "4da9b3090a8d5117414e47c686a3344d637b9bc0"}]}